<?xml version="1.0" encoding="utf-8" standalone="yes"?><response><header><resultCode>000</resultCode><resultMsg>OK</resultMsg></header><body><items><item><aptDong>101</aptDong><aptNm>성산</aptNm><aptSeq>52790-14</aptSeq><bonbun>0056</bonbun><bubun>0002</bubun><buildYear>1998</buildYear><buyerGbn>개인</buyerGbn><cdealDay> </cdealDay><cdealType> </cdealType><dealAmount>5,500</dealAmount><dealDay>28</dealDay><dealMonth>4</dealMonth><dealYear>2025</dealYear><dealingGbn>중개거래</dealingGbn><estateAgentSggNm>전북 고창군</estateAgentSggNm><excluUseAr>38.955</excluUseAr><floor>5</floor><jibun>56-2</jibun><landCd>1</landCd><landLeaseholdGbn>N</landLeaseholdGbn><rgstDate>25.05.12</rgstDate><roadNm>동리로</roadNm><roadNmBonbun>00172</roadNmBonbun><roadNmBubun>00014</roadNmBubun><roadNmCd>3279015</roadNmCd><roadNmSeq>01</roadNmSeq><roadNmSggCd>52790</roadNmSggCd><roadNmbCd>0</roadNmbCd><sggCd>52790</sggCd><slerGbn>개인</slerGbn><umdCd>25021</umdCd><umdNm>고창읍 읍내리</umdNm></item><item><aptDong>102</aptDong><aptNm>성산</aptNm><aptSeq>52790-14</aptSeq><bonbun>0056</bonbun><bubun>0002</bubun><buildYear>1998</buildYear><buyerGbn>개인</buyerGbn><cdealDay> </cdealDay><cdealType> </cdealType><dealAmount>8,300</dealAmount><dealDay>28</dealDay><dealMonth>4</dealMonth><dealYear>2025</dealYear><dealingGbn>중개거래</dealingGbn><estateAgentSggNm>전북 고창군</estateAgentSggNm><excluUseAr>59.808</excluUseAr><floor>2</floor><jibun>56-2</jibun><landCd>1</landCd><landLeaseholdGbn>N</landLeaseholdGbn><rgstDate>25.05.23</rgstDate><roadNm>동리로</roadNm><roadNmBonbun>00172</roadNmBonbun><roadNmBubun>00014</roadNmBubun><roadNmCd>3279015</roadNmCd><roadNmSeq>01</roadNmSeq><roadNmSggCd>52790</roadNmSggCd><roadNmbCd>0</roadNmbCd><sggCd>52790</sggCd><slerGbn>개인</slerGbn><umdCd>25021</umdCd><umdNm>고창읍 읍내리</umdNm></item><item><aptDong> </aptDong><aptNm>성산</aptNm><aptSeq>52790-14</aptSeq><bonbun>0056</bonbun><bubun>0002</bubun><buildYear>1998</buildYear><buyerGbn>개인</buyerGbn><cdealDay>25.05.09</cdealDay><cdealType>O</cdealType><dealAmount>5,500</dealAmount><dealDay>28</dealDay><dealMonth>4</dealMonth><dealYear>2025</dealYear><dealingGbn>중개거래</dealingGbn><estateAgentSggNm>전북 고창군</estateAgentSggNm><excluUseAr>59.808</excluUseAr><floor>5</floor><jibun>56-2</jibun><landCd>1</landCd><landLeaseholdGbn>N</landLeaseholdGbn><rgstDate> </rgstDate><roadNm>동리로</roadNm><roadNmBonbun>00172</roadNmBonbun><roadNmBubun>00014</roadNmBubun><roadNmCd>3279015</roadNmCd><roadNmSeq>01</roadNmSeq><roadNmSggCd>52790</roadNmSggCd><roadNmbCd>0</roadNmbCd><sggCd>52790</sggCd><slerGbn>개인</slerGbn><umdCd>25021</umdCd><umdNm>고창읍 읍내리</umdNm></item><item><aptDong>104</aptDong><aptNm>온천마을제일</aptNm><aptSeq>52790-17</aptSeq><bonbun>0586</bonbun><bubun>0000</bubun><buildYear>1999</buildYear><buyerGbn>개인</buyerGbn><cdealDay> </cdealDay><cdealType> </cdealType><dealAmount>18,300</dealAmount><dealDay>18</dealDay><dealMonth>4</dealMonth><dealYear>2025</dealYear><dealingGbn>직거래</dealingGbn><estateAgentSggNm> </estateAgentSggNm><excluUseAr>59.9646</excluUseAr><floor>14</floor><jibun>586</jibun><landCd>1</landCd><landLeaseholdGbn>N</landLeaseholdGbn><rgstDate>25.06.13</rgstDate><roadNm>월곡로</roadNm><roadNmBonbun>00083</roadNmBonbun><roadNmBubun>00000</roadNmBubun><roadNmCd>3279075</roadNmCd><roadNmSeq>01</roadNmSeq><roadNmSggCd>52790</roadNmSggCd><roadNmbCd>0</roadNmbCd><sggCd>52790</sggCd><slerGbn>개인</slerGbn><umdCd>25023</umdCd><umdNm>고창읍 월곡리</umdNm></item><item><aptDong>101</aptDong><aptNm>월곡주공</aptNm><aptSeq>52790-16</aptSeq><bonbun>0585</bonbun><bubun>0000</bubun><buildYear>2000</buildYear><buyerGbn>개인</buyerGbn><cdealDay> </cdealDay><cdealType> </cdealType><dealAmount>13,000</dealAmount><dealDay>24</dealDay><dealMonth>4</dealMonth><dealYear>2025</dealYear><dealingGbn>중개거래</dealingGbn><estateAgentSggNm>전북 고창군</estateAgentSggNm><excluUseAr>49.71</excluUseAr><floor>15</floor><jibun>585</jibun><landCd>1</landCd><landLeaseholdGbn>N</landLeaseholdGbn><rgstDate>25.07.31</rgstDate><roadNm>월곡1길</roadNm><roadNmBonbun>00043</roadNmBonbun><roadNmBubun>00000</roadNmBubun><roadNmCd>4637689</roadNmCd><roadNmSeq>01</roadNmSeq><roadNmSggCd>52790</roadNmSggCd><roadNmbCd>0</roadNmbCd><sggCd>52790</sggCd><slerGbn>개인</slerGbn><umdCd>25023</umdCd><umdNm>고창읍 월곡리</umdNm></item><item><aptDong>가</aptDong><aptNm>삼영남흥맨션</aptNm><aptSeq>52790-9</aptSeq><bonbun>1163</bonbun><bubun>0000</bubun><buildYear>1995</buildYear><buyerGbn>개인</buyerGbn><cdealDay> </cdealDay><cdealType> </cdealType><dealAmount>13,000</dealAmount><dealDay>22</dealDay><dealMonth>4</dealMonth><dealYear>2025</dealYear><dealingGbn>중개거래</dealingGbn><estateAgentSggNm>전북 고창군</estateAgentSggNm><excluUseAr>59.54</excluUseAr><floor>3</floor><jibun>1163</jibun><landCd>1</landCd><landLeaseholdGbn>N</landLeaseholdGbn><rgstDate>25.09.26</rgstDate><roadNm>중거리당산로</roadNm><roadNmBonbun>00085</roadNmBonbun><roadNmBubun>00000</roadNmBubun><roadNmCd>3279055</roadNmCd><roadNmSeq>01</roadNmSeq><roadNmSggCd>52790</roadNmSggCd><roadNmbCd>0</roadNmbCd><sggCd>52790</sggCd><slerGbn>개인</slerGbn><umdCd>25021</umdCd><umdNm>고창읍 읍내리</umdNm></item><item><aptDong>101</aptDong><aptNm>성산</aptNm><aptSeq>52790-14</aptSeq><bonbun>0056</bonbun><bubun>0002</bubun><buildYear>1998</buildYear><buyerGbn>개인</buyerGbn><cdealDay> </cdealDay><cdealType> </cdealType><dealAmount>6,700</dealAmount><dealDay>21</dealDay><dealMonth>4</dealMonth><dealYear>2025</dealYear><dealingGbn>중개거래</dealingGbn><estateAgentSggNm>전북 고창군</estateAgentSggNm><excluUseAr>38.955</excluUseAr><floor>1</floor><jibun>56-2</jibun><landCd>1</landCd><landLeaseholdGbn>N</landLeaseholdGbn><rgstDate>25.04.25</rgstDate><roadNm>동리로</roadNm><roadNmBonbun>00172</roadNmBonbun><roadNmBubun>00014</roadNmBubun><roadNmCd>3279015</roadNmCd><roadNmSeq>01</roadNmSeq><roadNmSggCd>52790</roadNmSggCd><roadNmbCd>0</roadNmbCd><sggCd>52790</sggCd><slerGbn>개인</slerGbn><umdCd>25021</umdCd><umdNm>고창읍 읍내리</umdNm></item><item><aptDong>1</aptDong><aptNm>상원모양맨션</aptNm><aptSeq>52790-10</aptSeq><bonbun>0410</bonbun><bubun>0009</bubun><buildYear>1995</buildYear><buyerGbn>개인</buyerGbn><cdealDay> </cdealDay><cdealType> </cdealType><dealAmount>8,700</dealAmount><dealDay>5</dealDay><dealMonth>4</dealMonth><dealYear>2025</dealYear><dealingGbn>직거래</dealingGbn><estateAgentSggNm> </estateAgentSggNm><excluUseAr>59.84</excluUseAr><floor>2</floor><jibun>410-9</jibun><landCd>1</landCd><landLeaseholdGbn>N</landLeaseholdGbn><rgstDate>25.04.21</rgstDate><roadNm>중거리당산로</roadNm><roadNmBonbun>00108</roadNmBonbun><roadNmBubun>00000</roadNmBubun><roadNmCd>3279055</roadNmCd><roadNmSeq>01</roadNmSeq><roadNmSggCd>52790</roadNmSggCd><roadNmbCd>0</roadNmbCd><sggCd>52790</sggCd><slerGbn>개인</slerGbn><umdCd>25021</umdCd><umdNm>고창읍 읍내리</umdNm></item><item><aptDong> </aptDong><aptNm>덕산진흥하이츠</aptNm><aptSeq>52790-6</aptSeq><bonbun>0518</bonbun><bubun>0005</bubun><buildYear>1993</buildYear><buyerGbn>개인</buyerGbn><cdealDay> </cdealDay><cdealType> </cdealType><dealAmount>13,000</dealAmount><dealDay>7</dealDay><dealMonth>4</dealMonth><dealYear>2025</dealYear><dealingGbn>직거래</dealingGbn><estateAgentSggNm> </estateAgentSggNm><excluUseAr>111.72</excluUseAr><floor>3</floor><jibun>518-5</jibun><landCd>1</landCd><landLeaseholdGbn>N</landLeaseholdGbn><rgstDate> </rgstDate><roadNm>남구4길</roadNm><roadNmBonbun>00027</roadNmBonbun><roadNmBubun>00000</roadNmBubun><roadNmCd>4637132</roadNmCd><roadNmSeq>01</roadNmSeq><roadNmSggCd>52790</roadNmSggCd><roadNmbCd>0</roadNmbCd><sggCd>52790</sggCd><slerGbn>개인</slerGbn><umdCd>25021</umdCd><umdNm>고창읍 읍내리</umdNm></item><item><aptDong>103</aptDong><aptNm>월곡주공</aptNm><aptSeq>52790-16</aptSeq><bonbun>0585</bonbun><bubun>0000</bubun><buildYear>2000</buildYear><buyerGbn>개인</buyerGbn><cdealDay> </cdealDay><cdealType> </cdealType><dealAmount>10,000</dealAmount><dealDay>15</dealDay><dealMonth>4</dealMonth><dealYear>2025</dealYear><dealingGbn>직거래</dealingGbn><estateAgentSggNm> </estateAgentSggNm><excluUseAr>39.5</excluUseAr><floor>4</floor><jibun>585</jibun><landCd>1</landCd><landLeaseholdGbn>N</landLeaseholdGbn><rgstDate>25.04.30</rgstDate><roadNm>월곡1길</roadNm><roadNmBonbun>00043</roadNmBonbun><roadNmBubun>00000</roadNmBubun><roadNmCd>4637689</roadNmCd><roadNmSeq>01</roadNmSeq><roadNmSggCd>52790</roadNmSggCd><roadNmbCd>0</roadNmbCd><sggCd>52790</sggCd><slerGbn>개인</slerGbn><umdCd>25023</umdCd><umdNm>고창읍 월곡리</umdNm></item><item><aptDong> </aptDong><aptNm>덕산진흥하이츠</aptNm><aptSeq>52790-6</aptSeq><bonbun>0518</bonbun><bubun>0005</bubun><buildYear>1993</buildYear><buyerGbn>개인</buyerGbn><cdealDay> </cdealDay><cdealType> </cdealType><dealAmount>14,000</dealAmount><dealDay>15</dealDay><dealMonth>4</dealMonth><dealYear>2025</dealYear><dealingGbn>중개거래</dealingGbn><estateAgentSggNm>전북 고창군</estateAgentSggNm><excluUseAr>59.4</excluUseAr><floor>5</floor><jibun>518-5</jibun><landCd>1</landCd><landLeaseholdGbn>N</landLeaseholdGbn><rgstDate>25.08.07</rgstDate><roadNm>남구4길</roadNm><roadNmBonbun>00027</roadNmBonbun><roadNmBubun>00000</roadNmBubun><roadNmCd>4637132</roadNmCd><roadNmSeq>01</roadNmSeq><roadNmSggCd>52790</roadNmSggCd><roadNmbCd>0</roadNmbCd><sggCd>52790</sggCd><slerGbn>개인</slerGbn><umdCd>25021</umdCd><umdNm>고창읍 읍내리</umdNm></item><item><aptDong> </aptDong><aptNm>진흥하이츠2차</aptNm><aptSeq>52790-2</aptSeq><bonbun>0224</bonbun><bubun>0003</bubun><buildYear>1995</buildYear><buyerGbn>개인</buyerGbn><cdealDay> </cdealDay><cdealType> </cdealType><dealAmount>16,500</dealAmount><dealDay>5</dealDay><dealMonth>4</dealMonth><dealYear>2025</dealYear><dealingGbn>중개거래</dealingGbn><estateAgentSggNm>전북 고창군</estateAgentSggNm><excluUseAr>59.92</excluUseAr><floor>14</floor><jibun>224-3</jibun><landCd>1</landCd><landLeaseholdGbn>N</landLeaseholdGbn><rgstDate>25.06.26</rgstDate><roadNm>모양성로</roadNm><roadNmBonbun>00108</roadNmBonbun><roadNmBubun>00000</roadNmBubun><roadNmCd>3279020</roadNmCd><roadNmSeq>01</roadNmSeq><roadNmSggCd>52790</roadNmSggCd><roadNmbCd>0</roadNmbCd><sggCd>52790</sggCd><slerGbn>개인</slerGbn><umdCd>25022</umdCd><umdNm>고창읍 교촌리</umdNm></item><item><aptDong>101</aptDong><aptNm>성산</aptNm><aptSeq>52790-14</aptSeq><bonbun>0056</bonbun><bubun>0002</bubun><buildYear>1998</buildYear><buyerGbn>개인</buyerGbn><cdealDay> </cdealDay><cdealType> </cdealType><dealAmount>6,600</dealAmount><dealDay>1</dealDay><dealMonth>4</dealMonth><dealYear>2025</dealYear><dealingGbn>중개거래</dealingGbn><estateAgentSggNm>전북 고창군</estateAgentSggNm><excluUseAr>38.955</excluUseAr><floor>2</floor><jibun>56-2</jibun><landCd>1</landCd><landLeaseholdGbn>N</landLeaseholdGbn><rgstDate>25.04.29</rgstDate><roadNm>동리로</roadNm><roadNmBonbun>00172</roadNmBonbun><roadNmBubun>00014</roadNmBubun><roadNmCd>3279015</roadNmCd><roadNmSeq>01</roadNmSeq><roadNmSggCd>52790</roadNmSggCd><roadNmbCd>0</roadNmbCd><sggCd>52790</sggCd><slerGbn>개인</slerGbn><umdCd>25021</umdCd><umdNm>고창읍 읍내리</umdNm></item></items><numOfRows>9999</numOfRows><pageNo>1</pageNo><totalCount>13</totalCount></body></response>